.gitignore
LICENSE
README.md
requirements.txt
telewrapper/__init__.py
telewrapper/core.py
telewrapper-0.0.5.dist-info/LICENSE
telewrapper-0.0.5.dist-info/METADATA
telewrapper-0.0.5.dist-info/WHEEL
telewrapper-0.0.5.dist-info/top_level.txt
telewrapper-0.0.5.dist-info/RECORD
