Metadata-Version: 2.1
Name: telewrapper
Version: 0.0.5
Summary: Telegram API wrapper based on Telethon.
Home-page: https://github.com/foxe6/telewrapper
Author: f̣ộx̣ệ6
Author-email: foxe6@protonmail.com
License: AGPL-3.0
Keywords: telegram telethon telewrapper bot api
Platform: UNKNOWN
Classifier: Programming Language :: Python :: 3.9
Classifier: Topic :: Utilities
Classifier: Natural Language :: English
Classifier: Intended Audience :: Developers
Classifier: License :: OSI Approved :: GNU Affero General Public License v3
Classifier: Operating System :: Microsoft :: Windows :: Windows 10
Requires-Python: >=3
License-File: LICENSE
Requires-Dist: omnitools (>=0.0.1)
Requires-Dist: telethon (>=0.0.1)
